<annotation>
	<folder>image</folder>
	<filename>T21WXS_20190413T153911_TCI_x9y14</filename>
	<size>
		<width>512</width>
		<height>512</height>
		<depth>3</depth>
	</size>
	<segmented>0</segmented>
	<object>
		<name>Iceberg</name>
		<pose>Unspecified</pose>
		<truncated>0</truncated>
		<difficult>0</difficult>
		<occluded>0</occluded>
		<bndbox>
			<xmin>456</xmin>
			<xmax>458</xmax>
			<ymin>55</ymin>
			<ymax>57</ymax>
		</bndbox>
	</object>
	<object>
		<name>Iceberg</name>
		<pose>Unspecified</pose>
		<truncated>0</truncated>
		<difficult>0</difficult>
		<occluded>0</occluded>
		<bndbox>
			<xmin>118</xmin>
			<xmax>121</xmax>
			<ymin>80</ymin>
			<ymax>82</ymax>
		</bndbox>
	</object>
	<object>
		<name>Iceberg</name>
		<pose>Unspecified</pose>
		<truncated>0</truncated>
		<difficult>0</difficult>
		<occluded>0</occluded>
		<bndbox>
			<xmin>95</xmin>
			<xmax>102</xmax>
			<ymin>108</ymin>
			<ymax>116</ymax>
		</bndbox>
	</object>
	<object>
		<name>Iceberg</name>
		<pose>Unspecified</pose>
		<truncated>0</truncated>
		<difficult>0</difficult>
		<occluded>0</occluded>
		<bndbox>
			<xmin>406</xmin>
			<xmax>407</xmax>
			<ymin>120</ymin>
			<ymax>121</ymax>
		</bndbox>
	</object>
	<object>
		<name>Iceberg</name>
		<pose>Unspecified</pose>
		<truncated>0</truncated>
		<difficult>0</difficult>
		<occluded>0</occluded>
		<bndbox>
			<xmin>405</xmin>
			<xmax>407</xmax>
			<ymin>125</ymin>
			<ymax>127</ymax>
		</bndbox>
	</object>
	<object>
		<name>Iceberg</name>
		<pose>Unspecified</pose>
		<truncated>0</truncated>
		<difficult>0</difficult>
		<occluded>0</occluded>
		<bndbox>
			<xmin>383</xmin>
			<xmax>384</xmax>
			<ymin>131</ymin>
			<ymax>132</ymax>
		</bndbox>
	</object>
	<object>
		<name>Iceberg</name>
		<pose>Unspecified</pose>
		<truncated>0</truncated>
		<difficult>0</difficult>
		<occluded>0</occluded>
		<bndbox>
			<xmin>197</xmin>
			<xmax>198</xmax>
			<ymin>235</ymin>
			<ymax>236</ymax>
		</bndbox>
	</object>
</annotation>